[
  {
    "tag": "单人",
    "count": 1,
    "games": [
      {
        "name": "Cities: Skylines II",
        "link": "/games/skylines2"
      }
    ]
  },
  {
    "tag": "城市营造",
    "count": 1,
    "games": [
      {
        "name": "Cities: Skylines II",
        "link": "/games/skylines2"
      }
    ]
  },
  {
    "tag": "建造",
    "count": 1,
    "games": [
      {
        "name": "Cities: Skylines II",
        "link": "/games/skylines2"
      }
    ]
  },
  {
    "tag": "模拟",
    "count": 1,
    "games": [
      {
        "name": "Cities: Skylines II",
        "link": "/games/skylines2"
      }
    ]
  },
  {
    "tag": "沙盒",
    "count": 1,
    "games": [
      {
        "name": "Cities: Skylines II",
        "link": "/games/skylines2"
      }
    ]
  },
  {
    "tag": "管理",
    "count": 1,
    "games": [
      {
        "name": "Cities: Skylines II",
        "link": "/games/skylines2"
      }
    ]
  },
  {
    "tag": "3D平台",
    "count": 1,
    "games": [
      {
        "name": "Split Fiction",
        "link": "/games/SplitFiction"
      }
    ]
  },
  {
    "tag": "分屏",
    "count": 1,
    "games": [
      {
        "name": "Split Fiction",
        "link": "/games/SplitFiction"
      }
    ]
  },
  {
    "tag": "动作冒险",
    "count": 1,
    "games": [
      {
        "name": "Split Fiction",
        "link": "/games/SplitFiction"
      }
    ]
  },
  {
    "tag": "合作",
    "count": 1,
    "games": [
      {
        "name": "Split Fiction",
        "link": "/games/SplitFiction"
      }
    ]
  },
  {
    "tag": "女性主角",
    "count": 1,
    "games": [
      {
        "name": "Split Fiction",
        "link": "/games/SplitFiction"
      }
    ]
  },
  {
    "tag": "挂机游戏",
    "count": 1,
    "games": [
      {
        "name": "动物栏：桌面牧场",
        "link": "/games/TinyPasture"
      }
    ]
  },
  {
    "tag": "农场模拟",
    "count": 1,
    "games": [
      {
        "name": "动物栏：桌面牧场",
        "link": "/games/TinyPasture"
      }
    ]
  },
  {
    "tag": "可爱",
    "count": 1,
    "games": [
      {
        "name": "动物栏：桌面牧场",
        "link": "/games/TinyPasture"
      }
    ]
  },
  {
    "tag": "像素图形",
    "count": 1,
    "games": [
      {
        "name": "动物栏：桌面牧场",
        "link": "/games/TinyPasture"
      }
    ]
  },
  {
    "tag": "点击游戏",
    "count": 1,
    "games": [
      {
        "name": "动物栏：桌面牧场",
        "link": "/games/TinyPasture"
      }
    ]
  }
]